MANIFEST.in
README.txt
setup.cfg
setup.py
Products/__init__.py
Products/__init__.pyc
Products.PloneRSS.egg-info/PKG-INFO
Products.PloneRSS.egg-info/SOURCES.txt
Products.PloneRSS.egg-info/dependency_links.txt
Products.PloneRSS.egg-info/entry_points.txt
Products.PloneRSS.egg-info/namespace_packages.txt
Products.PloneRSS.egg-info/not-zip-safe
Products.PloneRSS.egg-info/requires.txt
Products.PloneRSS.egg-info/top_level.txt
Products/PloneRSS/__init__.py
Products/PloneRSS/__init__.pyc
Products/PloneRSS/config.py
Products/PloneRSS/configure.zcml
Products/PloneRSS/credits.pt
Products/PloneRSS/getVersion.sh
Products/PloneRSS/profiles.zcml
Products/PloneRSS/refresh.txt
Products/PloneRSS/setuphandlers.py
Products/PloneRSS/tool.gif
Products/PloneRSS/version.txt
Products/PloneRSS/content/__init__.py
Products/PloneRSS/content/feedparser.py
Products/PloneRSS/content/interfaces.py
Products/PloneRSS/content/newsportlet.pt
Products/PloneRSS/content/newsportlet.py
Products/PloneRSS/content/rss_feed.py
Products/PloneRSS/content/rss_history.py
Products/PloneRSS/content/rss_instance.py
Products/PloneRSS/content/rss_item.py
Products/PloneRSS/content/rss_manager.py
Products/PloneRSS/content/rssparser.py
Products/PloneRSS/i18n/generated.pot
Products/PloneRSS/profiles/default/PloneRSS_marker.txt
Products/PloneRSS/profiles/default/catalog.xml
Products/PloneRSS/profiles/default/cssregistry.xml
Products/PloneRSS/profiles/default/factorytool.xml
Products/PloneRSS/profiles/default/import_steps.xml
Products/PloneRSS/profiles/default/jsregistry.xml
Products/PloneRSS/profiles/default/portlets.xml
Products/PloneRSS/profiles/default/skins.xml
Products/PloneRSS/profiles/default/types.xml
Products/PloneRSS/profiles/default/types/rss_feed.xml
Products/PloneRSS/profiles/default/types/rss_history.xml
Products/PloneRSS/profiles/default/types/rss_instance.xml
Products/PloneRSS/profiles/default/types/rss_item.xml
Products/PloneRSS/profiles/default/types/rss_manager.xml
Products/PloneRSS/skins/plonerss_images/book_icon.gif
Products/PloneRSS/skins/plonerss_images/rss.gif
Products/PloneRSS/skins/plonerss_images/rss_feed_icon.gif
Products/PloneRSS/skins/plonerss_images/rss_instance_icon.gif
Products/PloneRSS/skins/plonerss_images/rss_manager_icon.gif
Products/PloneRSS/skins/plonerss_styles/PloneRSS.css.dtml
