Metadata-Version: 1.0
Name: Products.PloneRSS
Version: 1.0.7beta
Summary: Plone RSS Integration
Home-page: http://encryptec.net/software-center/plonerss
Author: Gareth Bult
Author-email: gareth@encryptec.net
License: GPL
Keywords: plone rss
Platform: UNKNOWN
Classifier: Framework :: Plone
Classifier: Programming Language :: Python
Classifier: Topic :: Software Development :: Libraries :: Python Modules
